fastapi_simple_cachecontrol/__init__.py
fastapi_simple_cachecontrol/middleware.py
fastapi_simple_cachecontrol/types.py
fastapi_simple_cachecontrol-0.1.0.dist-info/METADATA
fastapi_simple_cachecontrol-0.1.0.dist-info/WHEEL
fastapi_simple_cachecontrol-0.1.0.dist-info/entry_points.txt
fastapi_simple_cachecontrol-0.1.0.dist-info/RECORD
