Metadata-Version: 2.1
Name: fastapi-simple-cachecontrol
Version: 0.1.0
Summary: Cache-Control header management for FastAPI
License: Apache-2.0
Author: Kazuya Takei
Author-email: myself@attakei.net
Requires-Python: >=3.7,<4.0
Classifier: License :: OSI Approved :: Apache Software License
Classifier: Programming Language :: Python :: 3
Classifier: Programming Language :: Python :: 3.7
Classifier: Programming Language :: Python :: 3.8
Classifier: Programming Language :: Python :: 3.9
Classifier: Programming Language :: Python :: 3.10
Classifier: Programming Language :: Python :: 3.11
Requires-Dist: fastapi
